LICENSE
README.md
lyywinauto.py
setup.py
lyywinauto.egg-info/PKG-INFO
lyywinauto.egg-info/SOURCES.txt
lyywinauto.egg-info/dependency_links.txt
lyywinauto.egg-info/requires.txt
lyywinauto.egg-info/top_level.txt