Metadata-Version: 2.1
Name: lyywinauto
Version: 1.1
Summary: userfull application for  lyy
Author: lyy
Author-email: 
License: MIT
License-File: LICENSE
Requires-Dist: pyautogui
